{"session_id": "bfa1b637-fe23-4bc8-95bd-5d692c3fa4fd", "state": "max_rounds_reached", "rounds": [{"round": 1, "multi": {"question": "\u751f\u6210\u5728\u7ebf\u6559\u5b66\u5e73\u53f0\u7684\u9700\u6c42\u5206\u6790\u6587\u6863", "responses": [{"model_id": "mock", "parsed": {"summary_points": [{"id": "p1", "text": "Echo of '(Answerer) Respond in JSON with fields: summary_points, detailed_explanation, evidence, reproducible_example. User question: \u751f\u6210\u5728\u7ebf\u6559\u5b66\u5e73\u53f0\u7684\u9700\u6c42\u5206\u6790\u6587\u6863. Context: .\n'", "confidence": "high"}, {"id": "p2", "text": "Mock systems return static data", "confidence": "medium"}, {"id": "p3", "text": "Use real adapters in production", "confidence": "medium"}], "detailed_explanation": "This is a mock structured response for testing pipelines.", "evidence": ["https://example.com/mock"], "reproducible_example": "print('mock')"}, "raw": "{\"summary_points\": [{\"id\": \"p1\", \"text\": \"Echo of '(Answerer) Respond in JSON with fields: summary_points, detailed_explanation, evidence, reproducible_example. User question: \\u751f\\u6210\\u5728\\u7ebf\\u6559\\u5b66\\u5e73\\u53f0\\u7684\\u9700\\u6c42\\u5206\\u6790\\u6587\\u6863. Context: .\\n'\", \"confidence\": \"high\"}, {\"id\": \"p2\", \"text\": \"Mock systems return static data\", \"confidence\": \"medium\"}, {\"id\": \"p3\", \"text\": \"Use real adapters in production\", \"confidence\": \"medium\"}], \"detailed_explanation\": \"This is a mock structured response for testing pipelines.\", \"evidence\": [\"https://example.com/mock\"], \"reproducible_example\": \"print('mock')\"}", "meta": {"model_id": "mock", "backend": "mock", "timestamp": "2026-01-14T16:02:32.814478+00:00", "model_name": "mock", "prompt_id": "answerer_v1", "prompt_version": "v1", "prompt_hash": "fb74d81a633edfd3ef061faf3d9a88a2e9f036956e4174c98d6d77f535269271", "prompt_used": "(Answerer) Respond in JSON with fields: summary_points, detailed_explanation, evidence, reproducible_example. User question: \u751f\u6210\u5728\u7ebf\u6559\u5b66\u5e73\u53f0\u7684\u9700\u6c42\u5206\u6790\u6587\u6863. Context: .\n", "request_id": "28e6fd6e9246a1b1", "latency_s": 0.0, "usage_tokens_estimate": 57}}, {"model_id": "hf", "parsed": {"summary_points": [{"id": "error", "text": "Error: HF adapter error after retries: Client error '410 Gone' for url 'https://api-inference.huggingface.co/models/bigscience/bloom-560m'\nFor more information check: https://developer.mozilla.org/en-US/docs/Web/HTTP/Status/410", "confidence": "low"}], "detailed_explanation": "This response indicates an error occurred: HF adapter error after retries: Client error '410 Gone' for url 'https://api-inference.huggingface.co/models/bigscience/bloom-560m'\nFor more information check: https://developer.mozilla.org/en-US/docs/Web/HTTP/Status/410", "evidence": [], "reproducible_example": ""}, "raw": "{\"summary_points\": [{\"id\": \"error\", \"text\": \"Error: HF adapter error after retries: Client error '410 Gone' for url 'https://api-inference.huggingface.co/models/bigscience/bloom-560m'\\nFor more information check: https://developer.mozilla.org/en-US/docs/Web/HTTP/Status/410\", \"confidence\": \"low\"}], \"detailed_explanation\": \"This response indicates an error occurred: HF adapter error after retries: Client error '410 Gone' for url 'https://api-inference.huggingface.co/models/bigscience/bloom-560m'\\nFor more information check: https://developer.mozilla.org/en-US/docs/Web/HTTP/Status/410\", \"evidence\": [], \"reproducible_example\": \"\"}", "meta": {"model_id": "hf", "backend": "hf", "timestamp": "2026-01-14T16:02:34.793631+00:00", "model_name": "bigscience/bloom-560m", "prompt_id": "answerer_v1", "prompt_version": "v1", "prompt_hash": "fb74d81a633edfd3ef061faf3d9a88a2e9f036956e4174c98d6d77f535269271", "prompt_used": "(Answerer) Respond in JSON with fields: summary_points, detailed_explanation, evidence, reproducible_example. User question: \u751f\u6210\u5728\u7ebf\u6559\u5b66\u5e73\u53f0\u7684\u9700\u6c42\u5206\u6790\u6587\u6863. Context: .\n", "request_id": "7d4ace6471c6201a", "latency_s": 1.9772, "usage_tokens_estimate": 50}}], "prompt_id": "answerer_v1", "prompt_version": "v1"}, "report": null, "contradictions": 0, "agreement_score": null}, {"round": 1, "multi": {"question": "\u751f\u6210\u5728\u7ebf\u6559\u5b66\u5e73\u53f0\u7684\u9700\u6c42\u5206\u6790\u6587\u6863", "responses": [{"model_id": "mock", "parsed": {"summary_points": [{"id": "p1", "text": "Echo of '(Answerer) Respond in JSON with fields: summary_points, detailed_explanation, evidence, reproducible_example. User question: \u751f\u6210\u5728\u7ebf\u6559\u5b66\u5e73\u53f0\u7684\u9700\u6c42\u5206\u6790\u6587\u6863. Context: .\n'", "confidence": "high"}, {"id": "p2", "text": "Mock systems return static data", "confidence": "medium"}, {"id": "p3", "text": "Use real adapters in production", "confidence": "medium"}], "detailed_explanation": "This is a mock structured response for testing pipelines.", "evidence": ["https://example.com/mock"], "reproducible_example": "print('mock')"}, "raw": "{\"summary_points\": [{\"id\": \"p1\", \"text\": \"Echo of '(Answerer) Respond in JSON with fields: summary_points, detailed_explanation, evidence, reproducible_example. User question: \\u751f\\u6210\\u5728\\u7ebf\\u6559\\u5b66\\u5e73\\u53f0\\u7684\\u9700\\u6c42\\u5206\\u6790\\u6587\\u6863. Context: .\\n'\", \"confidence\": \"high\"}, {\"id\": \"p2\", \"text\": \"Mock systems return static data\", \"confidence\": \"medium\"}, {\"id\": \"p3\", \"text\": \"Use real adapters in production\", \"confidence\": \"medium\"}], \"detailed_explanation\": \"This is a mock structured response for testing pipelines.\", \"evidence\": [\"https://example.com/mock\"], \"reproducible_example\": \"print('mock')\"}", "meta": {"model_id": "mock", "backend": "mock", "timestamp": "2026-01-14T16:02:34.798989+00:00", "model_name": "mock", "prompt_id": "answerer_v1", "prompt_version": "v1", "prompt_hash": "fb74d81a633edfd3ef061faf3d9a88a2e9f036956e4174c98d6d77f535269271", "prompt_used": "(Answerer) Respond in JSON with fields: summary_points, detailed_explanation, evidence, reproducible_example. User question: \u751f\u6210\u5728\u7ebf\u6559\u5b66\u5e73\u53f0\u7684\u9700\u6c42\u5206\u6790\u6587\u6863. Context: .\n", "request_id": "e89debc309ef57fc", "latency_s": 0.0, "usage_tokens_estimate": 57}}, {"model_id": "hf", "parsed": {"summary_points": [{"id": "error", "text": "Error: HF adapter error after retries: Client error '410 Gone' for url 'https://api-inference.huggingface.co/models/bigscience/bloom-560m'\nFor more information check: https://developer.mozilla.org/en-US/docs/Web/HTTP/Status/410", "confidence": "low"}], "detailed_explanation": "This response indicates an error occurred: HF adapter error after retries: Client error '410 Gone' for url 'https://api-inference.huggingface.co/models/bigscience/bloom-560m'\nFor more information check: https://developer.mozilla.org/en-US/docs/Web/HTTP/Status/410", "evidence": [], "reproducible_example": ""}, "raw": "{\"summary_points\": [{\"id\": \"error\", \"text\": \"Error: HF adapter error after retries: Client error '410 Gone' for url 'https://api-inference.huggingface.co/models/bigscience/bloom-560m'\\nFor more information check: https://developer.mozilla.org/en-US/docs/Web/HTTP/Status/410\", \"confidence\": \"low\"}], \"detailed_explanation\": \"This response indicates an error occurred: HF adapter error after retries: Client error '410 Gone' for url 'https://api-inference.huggingface.co/models/bigscience/bloom-560m'\\nFor more information check: https://developer.mozilla.org/en-US/docs/Web/HTTP/Status/410\", \"evidence\": [], \"reproducible_example\": \"\"}", "meta": {"model_id": "hf", "backend": "hf", "timestamp": "2026-01-14T16:02:36.767563+00:00", "model_name": "bigscience/bloom-560m", "prompt_id": "answerer_v1", "prompt_version": "v1", "prompt_hash": "fb74d81a633edfd3ef061faf3d9a88a2e9f036956e4174c98d6d77f535269271", "prompt_used": "(Answerer) Respond in JSON with fields: summary_points, detailed_explanation, evidence, reproducible_example. User question: \u751f\u6210\u5728\u7ebf\u6559\u5b66\u5e73\u53f0\u7684\u9700\u6c42\u5206\u6790\u6587\u6863. Context: .\n", "request_id": "ce8df761f7fdde95", "latency_s": 1.9639, "usage_tokens_estimate": 50}}], "prompt_id": "answerer_v1", "prompt_version": "v1"}, "report": {"confirmed": [{"cluster_id": "['mock_p1', 'mock_p3', 'hf_error']", "points": [{"id": "mock_p1", "model_id": "mock", "text": "Echo of '(Answerer) Respond in JSON with fields: summary_points, detailed_explanation, evidence, reproducible_example. User question: \u751f\u6210\u5728\u7ebf\u6559\u5b66\u5e73\u53f0\u7684\u9700\u6c42\u5206\u6790\u6587\u6863. Context: .\n'"}, {"id": "mock_p3", "model_id": "mock", "text": "Use real adapters in production"}, {"id": "hf_error", "model_id": "hf", "text": "Error: HF adapter error after retries: Client error '410 Gone' for url 'https://api-inference.huggingface.co/models/bigscience/bloom-560m'\nFor more information check: https://developer.mozilla.org/en-US/docs/Web/HTTP/Status/410"}], "models": ["hf", "mock"]}, {"cluster_id": "['mock_p2']", "points": [{"id": "mock_p2", "model_id": "mock", "text": "Mock systems return static data"}], "models": ["mock"]}], "contradictions": [], "followups": [], "recommendation": "continue_rounds", "cross_eval": [{"cluster_id": "['mock_p1', 'mock_p3', 'hf_error']", "a": {"id": "mock_p1", "model_id": "mock"}, "b": {"id": "hf_error", "model_id": "hf"}, "judgement": "uncertain", "reason": "Heuristic NLI -> neutral", "confidence": "medium", "prompt_used": true}, {"cluster_id": "['mock_p1', 'mock_p3', 'hf_error']", "a": {"id": "mock_p3", "model_id": "mock"}, "b": {"id": "hf_error", "model_id": "hf"}, "judgement": "uncertain", "reason": "Heuristic NLI -> neutral", "confidence": "medium", "prompt_used": true}], "nli": [{"cluster_id": "['mock_p1', 'mock_p3', 'hf_error']", "a": {"id": "mock_p1", "model_id": "mock"}, "b": {"id": "mock_p3", "model_id": "mock"}, "label": "entailment"}, {"cluster_id": "['mock_p1', 'mock_p3', 'hf_error']", "a": {"id": "mock_p1", "model_id": "mock"}, "b": {"id": "hf_error", "model_id": "hf"}, "label": "neutral"}, {"cluster_id": "['mock_p1', 'mock_p3', 'hf_error']", "a": {"id": "mock_p3", "model_id": "mock"}, "b": {"id": "hf_error", "model_id": "hf"}, "label": "neutral"}]}, "contradictions": 0, "agreement_score": 1.0}], "final_report": {"confirmed": [{"cluster_id": "['mock_p1', 'mock_p3', 'hf_error']", "points": [{"id": "mock_p1", "model_id": "mock", "text": "Echo of '(Answerer) Respond in JSON with fields: summary_points, detailed_explanation, evidence, reproducible_example. User question: \u751f\u6210\u5728\u7ebf\u6559\u5b66\u5e73\u53f0\u7684\u9700\u6c42\u5206\u6790\u6587\u6863. Context: .\n'"}, {"id": "mock_p3", "model_id": "mock", "text": "Use real adapters in production"}, {"id": "hf_error", "model_id": "hf", "text": "Error: HF adapter error after retries: Client error '410 Gone' for url 'https://api-inference.huggingface.co/models/bigscience/bloom-560m'\nFor more information check: https://developer.mozilla.org/en-US/docs/Web/HTTP/Status/410"}], "models": ["hf", "mock"]}, {"cluster_id": "['mock_p2']", "points": [{"id": "mock_p2", "model_id": "mock", "text": "Mock systems return static data"}], "models": ["mock"]}], "contradictions": [], "followups": [], "recommendation": "continue_rounds", "cross_eval": [{"cluster_id": "['mock_p1', 'mock_p3', 'hf_error']", "a": {"id": "mock_p1", "model_id": "mock"}, "b": {"id": "hf_error", "model_id": "hf"}, "judgement": "uncertain", "reason": "Heuristic NLI -> neutral", "confidence": "medium", "prompt_used": true}, {"cluster_id": "['mock_p1', 'mock_p3', 'hf_error']", "a": {"id": "mock_p3", "model_id": "mock"}, "b": {"id": "hf_error", "model_id": "hf"}, "judgement": "uncertain", "reason": "Heuristic NLI -> neutral", "confidence": "medium", "prompt_used": true}], "nli": [{"cluster_id": "['mock_p1', 'mock_p3', 'hf_error']", "a": {"id": "mock_p1", "model_id": "mock"}, "b": {"id": "mock_p3", "model_id": "mock"}, "label": "entailment"}, {"cluster_id": "['mock_p1', 'mock_p3', 'hf_error']", "a": {"id": "mock_p1", "model_id": "mock"}, "b": {"id": "hf_error", "model_id": "hf"}, "label": "neutral"}, {"cluster_id": "['mock_p1', 'mock_p3', 'hf_error']", "a": {"id": "mock_p3", "model_id": "mock"}, "b": {"id": "hf_error", "model_id": "hf"}, "label": "neutral"}]}}